WdSql/MySQL.py
WdSql/SQLserver.py
WdSql/__init__.py
WdSql/error.py
WdSql/objects.py
WdSql/utils.py
WdSql-0.0.4.dist-info/LICENSE
WdSql-0.0.4.dist-info/METADATA
WdSql-0.0.4.dist-info/WHEEL
WdSql-0.0.4.dist-info/top_level.txt
WdSql-0.0.4.dist-info/RECORD
